{
    "\/components\/points\/includes\/functions.php": {
        "size": 1634,
        "hash": "268e6793315b680fbdb33bc00ee9ca31",
        "errors": false
    },
    "\/components\/points\/includes\/gateways\/points.php": {
        "size": 6363,
        "hash": "65b62e80d18b45a9d32e820116ec2aaf",
        "errors": false
    },
    "\/components\/points\/includes\/hooks\/order-complete.php": {
        "size": 3315,
        "hash": "c49ecfbebd7ac401f1df2cea4b7c5be9",
        "errors": false
    },
    "\/components\/points\/points.php": {
        "size": 658,
        "hash": "1388301e57afeb3f7cf94bf9dd10ab7c",
        "errors": false
    },
    "\/includes\/constants.php": {
        "size": 455,
        "hash": "046d7fd2713c4dda759a6b29c9c44c5b",
        "errors": false
    },
    "\/includes\/functions.php": {
        "size": 1023,
        "hash": "bfe8e5c902b39c9cfdd92efc2c264497",
        "errors": false
    },
    "\/uninstall.php": {
        "size": 490,
        "hash": "0e88f799d2a463e3908f6e6c27d559ba",
        "errors": false
    },
    "\/woocommerce.php": {
        "size": 1115,
        "hash": "95040ee52d7213af866c28f8fc5e1414",
        "errors": false
    }
}